README.txt
setup.cfg
setup.py
docs/HISTORY.txt
docs/INSTALL.txt
docs/LICENSE.GPL
docs/LICENSE.txt
raptus/__init__.py
raptus.showcase.egg-info/PKG-INFO
raptus.showcase.egg-info/SOURCES.txt
raptus.showcase.egg-info/dependency_links.txt
raptus.showcase.egg-info/entry_points.txt
raptus.showcase.egg-info/namespace_packages.txt
raptus.showcase.egg-info/not-zip-safe
raptus.showcase.egg-info/requires.txt
raptus.showcase.egg-info/top_level.txt
raptus/showcase/__init__.py
raptus/showcase/config.py
raptus/showcase/configure.zcml
raptus/showcase/events.py
raptus/showcase/interfaces.py
raptus/showcase/skins.zcml
raptus/showcase/browser/__init__.py
raptus/showcase/browser/configure.zcml
raptus/showcase/browser/views.py
raptus/showcase/browser/images/showcaseImage_icon.png
raptus/showcase/browser/images/showcase_icon.png
raptus/showcase/browser/javascript/showcase.js
raptus/showcase/browser/templates/showcase.pt
raptus/showcase/browser/templates/showcaseFolder.pt
raptus/showcase/browser/templates/showcaseImage.pt
raptus/showcase/browser/templates/showcase_macros.pt
raptus/showcase/content/__init__.py
raptus/showcase/content/configure.zcml
raptus/showcase/content/showcase.py
raptus/showcase/content/showcaseImage.py
raptus/showcase/i18n/raptus.showcase-de.po
raptus/showcase/i18n/raptus.showcase.pot
raptus/showcase/profiles/default/factorytool.xml
raptus/showcase/profiles/default/metadata.xml
raptus/showcase/profiles/default/propertiestool.xml
raptus/showcase/profiles/default/rolemap.xml
raptus/showcase/profiles/default/skins.xml
raptus/showcase/profiles/default/types.xml
raptus/showcase/profiles/default/types/Folder.xml
raptus/showcase/profiles/default/types/Showcase.xml
raptus/showcase/profiles/default/types/ShowcaseImage.xml
raptus/showcase/skins/showcase/showcase.css.dtml
raptus/showcase/skins/showcase/showcasefolder.css.dtml
raptus/showcase/skins/showcaseboxwidget/jquery.leftClick.js
raptus/showcase/skins/showcaseboxwidget/jquery.rightClick.js
raptus/showcase/skins/showcaseboxwidget/showcaseboxwidget.css
raptus/showcase/skins/showcaseboxwidget/showcaseboxwidget.js
raptus/showcase/skins/showcaseboxwidget/showcaseboxwidget.pt