Metadata-Version: 1.0
Name: raptus.showcase
Version: 0.5a1
Summary: showcase
Home-page: http://raptus.com
Author: Raptus AG
Author-email: info@raptus.com
License: GPL
Platform: UNKNOWN
Classifier: Framework :: Plone
Classifier: Programming Language :: Python
Classifier: Topic :: Software Development :: Libraries :: Python Modules
